registerMap/VERSION
registerMap/__init__.py
registerMap/exceptions.py
registerMap/exporter.py
registerMap/registerMap.py
registerMap/base/__init__.py
registerMap/base/parameters.py
registerMap/base/tests/__init__.py
registerMap/base/tests/testElementsParameter.py
registerMap/base/tests/testModulesParameter.py
registerMap/constraints/__init__.py
registerMap/constraints/constraintTable.py
registerMap/constraints/constraints.py
registerMap/constraints/tests/__init__.py
registerMap/constraints/tests/testAlignmentConstraint.py
registerMap/constraints/tests/testConstraintTable.py
registerMap/constraints/tests/testFixedAddressConstraint.py
registerMap/constraints/tests/testFixedSizeConstraint.py
registerMap/export/__init__.py
registerMap/export/arguments.py
registerMap/export/exporters.py
registerMap/export/options.py
registerMap/export/base/__init__.py
registerMap/export/base/field.py
registerMap/export/base/interface.py
registerMap/export/base/memory.py
registerMap/export/base/module.py
registerMap/export/base/output.py
registerMap/export/base/register.py
registerMap/export/base/registerMap.py
registerMap/export/base/template.py
registerMap/export/base/tests/__init__.py
registerMap/export/base/tests/mocks.py
registerMap/export/base/tests/testExportFieldBase.py
registerMap/export/base/tests/testExportMemoryBase.py
registerMap/export/base/tests/testExportModuleBase.py
registerMap/export/base/tests/testExportOutputBase.py
registerMap/export/base/tests/testExportRegisterBase.py
registerMap/export/base/tests/testExportRegisterContiguousFields.py
registerMap/export/base/tests/testExportRegisterMapBase.py
registerMap/export/base/tests/testExportTemplateBase.py
registerMap/export/c/__init__.py
registerMap/export/c/arguments.py
registerMap/export/c/options.py
registerMap/export/c/registerMap.py
registerMap/export/c/elements/__init__.py
registerMap/export/c/elements/field.py
registerMap/export/c/elements/memory.py
registerMap/export/c/elements/module.py
registerMap-0.6.0.dist-info/entry_points.txt
registerMap-0.6.0.dist-info/LICENSE
registerMap-0.6.0.dist-info/WHEEL
registerMap-0.6.0.dist-info/METADATA
registerMap-0.6.0.dist-info/RECORD
