Metadata-Version: 2.1
Name: registerMap
Version: 0.6.0
Summary: A Python 3 framework for creating and maintaining register maps for integrated circuit design and embedded
Home-page: https://gitlab.com/registerMap/registerMap
License: UNKNOWN
Keywords: registermap register digital electronic design csr control status
Author: Russell Smiley
Author-email: im.russell.smiley@gmail.com
Requires-Python: >=3.6
Classifier: License :: OSI Approved :: GNU General Public License v3 or later (GPLv3+)
Requires-Dist: jinja2
Requires-Dist: pyyaml
Requires-Dist: nose; extra == "dev"
Requires-Dist: nose-cov; extra == "dev"
Requires-Dist: nosehtmloutput-2; extra == "dev"
Provides-Extra: .none
Provides-Extra: dev
